[{"id":"021","descricao":"PRODUÇÃO FLORESTAL - FLORESTAS PLANTADAS","divisao":{"id":"02","descricao":"PRODUÇÃO FLORESTAL","secao":{"id":"A","descricao":"AGRICULTURA, PECUÁRIA, PRODUÇÃO FLORESTAL, PESCA E AQÜICULTURA"}}}, {"id":"022","descricao":"PRODUÇÃO FLORESTAL - FLORESTAS NATIVAS","divisao":{"id":"02","descricao":"PRODUÇÃO FLORESTAL","secao":{"id":"A","descricao":"AGRICULTURA, PECUÁRIA, PRODUÇÃO FLORESTAL, PESCA E AQÜICULTURA"}}}, {"id":"023","descricao":"ATIVIDADES DE APOIO À PRODUÇÃO FLORESTAL","divisao":{"id":"02","descricao":"PRODUÇÃO FLORESTAL","secao":{"id":"A","descricao":"AGRICULTURA, PECUÁRIA, PRODUÇÃO FLORESTAL, PESCA E AQÜICULTURA"}}}]
