[{"id":"291","descricao":"FABRICAÇÃO DE AUTOMÓVEIS, CAMIONETAS E UTILITÁRIOS","divisao":{"id":"29","descricao":"FABRICAÇÃO DE VEÍCULOS AUTOMOTORES, REBOQUES E CARROCERIAS","secao":{"id":"C","descricao":"INDÚSTRIAS DE TRANSFORMAÇÃO"}}}, {"id":"292","descricao":"FABRICAÇÃO DE CAMINHÕES E ÔNIBUS","divisao":{"id":"29","descricao":"FABRICAÇÃO DE VEÍCULOS AUTOMOTORES, REBOQUES E CARROCERIAS","secao":{"id":"C","descricao":"INDÚSTRIAS DE TRANSFORMAÇÃO"}}}, {"id":"293","descricao":"FABRICAÇÃO DE CABINES, CARROCERIAS E REBOQUES PARA VEÍCULOS AUTOMOTORES","divisao":{"id":"29","descricao":"FABRICAÇÃO DE VEÍCULOS AUTOMOTORES, REBOQUES E CARROCERIAS","secao":{"id":"C","descricao":"INDÚSTRIAS DE TRANSFORMAÇÃO"}}}, {"id":"294","descricao":"FABRICAÇÃO DE PEÇAS E ACESSÓRIOS PARA VEÍCULOS AUTOMOTORES","divisao":{"id":"29","descricao":"FABRICAÇÃO DE VEÍCULOS AUTOMOTORES, REBOQUES E CARROCERIAS","secao":{"id":"C","descricao":"INDÚSTRIAS DE TRANSFORMAÇÃO"}}}, {"id":"295","descricao":"RECONDICIONAMENTO E RECUPERAÇÃO DE MOTORES PARA VEÍCULOS AUTOMOTORES","divisao":{"id":"29","descricao":"FABRICAÇÃO DE VEÍCULOS AUTOMOTORES, REBOQUES E CARROCERIAS","secao":{"id":"C","descricao":"INDÚSTRIAS DE TRANSFORMAÇÃO"}}}]
